universal_xmind_converter.py
validate_xmind_structure.py
xmind_ai_extensions.py
xmind_core_engine.py
xmind_mcp_server.py
xmind_types.py
xmind_writer.py
scripts/translate_xmind_titles.py
scripts/upload_pypi.py
tests/alias_validate.py
tests/run_all_tests.py
tests/test_batch.py
tests/test_client.py
tests/test_core.py
tests/test_setup.py
xmind_mcp/__init__.py
xmind_mcp/__main__.py
iflow_mcp_master_frank_xmindmcp-1.3.9.dist-info/METADATA
iflow_mcp_master_frank_xmindmcp-1.3.9.dist-info/WHEEL
iflow_mcp_master_frank_xmindmcp-1.3.9.dist-info/entry_points.txt
iflow_mcp_master_frank_xmindmcp-1.3.9.dist-info/licenses/LICENSE
iflow_mcp_master_frank_xmindmcp-1.3.9.dist-info/RECORD
