Metadata-Version: 2.4
Name: iflow-mcp_master-frank_xmindmcp
Version: 1.3.9
Summary: XMind MCP Server - 思维导图创建/分析/转换（别名兼容、递归列举）
Project-URL: Homepage, https://github.com/Master-Frank/XmindMcp
Project-URL: Repository, https://github.com/Master-Frank/XmindMcp.git
Project-URL: Issues, https://github.com/Master-Frank/XmindMcp/issues
Author-email: XMind MCP Project <xmind-mcp@example.com>
License: MIT
License-File: LICENSE
Keywords: ai,converter,mcp,mindmap,xmind
Classifier: Development Status :: 4 - Beta
Classifier: Intended Audience :: Developers
Classifier: License :: OSI Approved :: MIT License
Classifier: Programming Language :: Python :: 3
Classifier: Programming Language :: Python :: 3.8
Classifier: Programming Language :: Python :: 3.9
Classifier: Programming Language :: Python :: 3.10
Classifier: Programming Language :: Python :: 3.11
Classifier: Programming Language :: Python :: 3.12
Classifier: Topic :: Office/Business :: Groupware
Classifier: Topic :: Software Development :: Libraries :: Python Modules
Classifier: Topic :: Text Processing :: Markup
Requires-Python: >=3.8
Requires-Dist: beautifulsoup4
Requires-Dist: deep-translator>=1.11.4
Requires-Dist: mcp[cli]>=1.3.0
Requires-Dist: openpyxl
Requires-Dist: python-docx
